.project
AUTHORS.rst
HISTORY.rst
LICENSE
MANIFEST.in
README.rst
setup.py
CudaPyInt.egg-info/PKG-INFO
CudaPyInt.egg-info/SOURCES.txt
CudaPyInt.egg-info/dependency_links.txt
CudaPyInt.egg-info/not-zip-safe
CudaPyInt.egg-info/requires.txt
CudaPyInt.egg-info/top_level.txt
Tests/dummy.cu
Tests/test_CodeGenerator.py
Tests/test_CulsodaCodeGenerator.py
benchmarks/einsteinboltzmann/cudapyint_benchmark.sbatch
benchmarks/einsteinboltzmann/cudapyint_benchmark.sh
benchmarks/einsteinboltzmann/eta_a
benchmarks/einsteinboltzmann/ha_a
benchmarks/einsteinboltzmann/ha_y
benchmarks/einsteinboltzmann/rec_a
benchmarks/einsteinboltzmann/rec_xe
benchmarks/einsteinboltzmann/run_benchmarks_cmd2.py
cudapyint/CodeGenerator.py
cudapyint/CulsodaCodeGenerator.py
cudapyint/ODESolver.py
cudapyint/ODESolverSharedMemory.py
cudapyint/ParallelODESolver.py
cudapyint/ParallelODESolverSharedMemory.py
cudapyint/PyCudaUtils.py
cudapyint/Solver.py
cudapyint/__init__.py
cudapyint/cuLsoda_all.cu
cudapyint/cuLsoda_main.cu
cudapyint/cuLsoda_main_parallel.cu
cudapyint/cuLsoda_main_parallel_shared_memory.cu
cudapyint/cuLsoda_main_shared_mem.cu
doc/Makefile
doc/build/doctrees/api.doctree
doc/build/doctrees/environment.pickle
doc/build/doctrees/index.doctree
doc/build/doctrees/user/install.doctree
doc/build/html/.buildinfo
doc/build/html/api.html
doc/build/html/genindex.html
doc/build/html/index.html
doc/build/html/objects.inv
doc/build/html/py-modindex.html
doc/build/html/search.html
doc/build/html/searchindex.js
doc/build/html/_modules/index.html
doc/build/html/_modules/cudapyint/CodeGenerator.html
doc/build/html/_modules/cudapyint/CulsodaCodeGenerator.html
doc/build/html/_modules/cudapyint/ODESolver.html
doc/build/html/_modules/cudapyint/ODESolverSharedMemory.html
doc/build/html/_modules/cudapyint/ParallelODESolver.html
doc/build/html/_modules/cudapyint/ParallelODESolverSharedMemory.html
doc/build/html/_modules/cudapyint/PyCudaUtils.html
doc/build/html/_modules/cudapyint/Solver.html
doc/build/html/_sources/api.txt
doc/build/html/_sources/index.txt
doc/build/html/_sources/user/install.txt
doc/build/html/_static/ajax-loader.gif
doc/build/html/_static/basic.css
doc/build/html/_static/comment-bright.png
