Metadata-Version: 1.1
Name: CudaPyInt
Version: 0.0.1
Summary: GPU based parallel ode solver
Home-page: http://www.fhnw.ch
Author: Joel Akeret
Author-email: jakeret@phys.ethz.ch
License: GPLv3
Platform: UNKNOWN
Classifier: Development Status :: 3 - Alpha
Classifier: Intended Audience :: Science/Research
Classifier: Operating System :: OS Independent
Classifier: Programming Language :: Python
Classifier: Programming Language :: C
